st_weaviate_connection/__init__.py
st_weaviate_connection/connection.py
st_weaviate_connection-0.1.0.dist-info/LICENSE
st_weaviate_connection-0.1.0.dist-info/METADATA
st_weaviate_connection-0.1.0.dist-info/WHEEL
st_weaviate_connection-0.1.0.dist-info/RECORD
