Metadata-Version: 2.1
Name: st-weaviate-connection
Version: 0.1.0
Summary: A python package that provides a custom streamlit connection to query data from weaviate, the AI native vector database
License: BSD-3-Clause license
Author: hsm207
Author-email: hsm207@users.noreply.github.com
Requires-Python: >=3.11,<4.0
Classifier: License :: Other/Proprietary License
Classifier: Programming Language :: Python :: 3
Classifier: Programming Language :: Python :: 3.11
Classifier: Programming Language :: Python :: 3.12
Requires-Dist: streamlit (>=1.37.0,<2.0.0)
Requires-Dist: weaviate-client (>=4.7.1,<5.0.0)
